<measure>
  <schema_version>3.0</schema_version>
  <name>glhe_pro_setup_export_loadsfor_ground_heat_exchanger_sizing</name>
  <uid>15a9a421-1395-4584-9237-a0bc4c7bc69c</uid>
  <version_id>43c1ee49-8016-45cb-bd2e-83bd5d5cadbd</version_id>
  <version_modified>20161107T222250Z</version_modified>
  <xml_checksum>350B6836</xml_checksum>
  <class_name>GLHEProSetupExportLoadsforGroundHeatExchangerSizing</class_name>
  <display_name>GLHEProSetupExportLoadsforGroundHeatExchangerSizing</display_name>
  <description>Requests that EnergyPlus output the district heating and district cooling rates at an hourly interval.  These rates will be used by the Measure called "GLHEPro Export Loads for Ground Heat Exchanger Sizing" to create a .gt1 file that is used by GLHEPro to help designers size ground heat exchangers.  The ground heat exchanger object exported from GLHEPro can then be re-imported into OpenStudio to replace the district heating and district cooling objects.  This is done by the Measure callled "GLHEPro GFunction Import</description>
  <modeler_description>The model should be set up so that both the heating and cooling coils for the zone-level water source heat pumps are connected to the demand side of the plant loop, and that the supply side of the plant loop contains a district heating and district cooling object.  The .gt1 file that is exported will be named after the plant loop.</modeler_description>
  <arguments/>
  <outputs/>
  <provenances/>
  <tags>
    <tag>Reporting.QAQC</tag>
  </tags>
  <attributes>
    <attribute>
      <name>Measure Function</name>
      <value>Measure</value>
      <datatype>string</datatype>
    </attribute>
    <attribute>
      <name>Requires EnergyPlus Results</name>
      <value>false</value>
      <datatype>boolean</datatype>
    </attribute>
    <attribute>
      <name>Measure Type</name>
      <value>ModelMeasure</value>
      <datatype>string</datatype>
    </attribute>
    <attribute>
      <name>Uses SketchUp API</name>
      <value>false</value>
      <datatype>boolean</datatype>
    </attribute>
  </attributes>
  <files>
    <file>
      <version>
        <software_program>OpenStudio</software_program>
        <identifier>1.0.0</identifier>
        <min_compatible>1.8.0</min_compatible>
      </version>
      <filename>measure.rb</filename>
      <filetype>rb</filetype>
      <usage_type>script</usage_type>
      <checksum>F4B722F5</checksum>
    </file>
  </files>
</measure>
